kasa_crypt/__init__.py
kasa_crypt/_crypt_impl.c
kasa_crypt/_crypt_impl.cpython-313-aarch64-linux-musl.so
kasa_crypt/_crypt_impl.pyx
kasa_crypt/crypt_wrapper.h
kasa_crypt/py.typed
kasa_crypt/python_impl.py
kasa_crypt-0.6.3.dist-info/LICENSE
kasa_crypt-0.6.3.dist-info/METADATA
kasa_crypt-0.6.3.dist-info/WHEEL
kasa_crypt-0.6.3.dist-info/RECORD
