Metadata-Version: 2.3
Name: kasa-crypt
Version: 0.6.3
Summary: Fast kasa crypt
License: Apache-2.0
Author: J. Nick Koston
Author-email: nick@koston.org
Requires-Python: >=3.9
Classifier: Development Status :: 2 - Pre-Alpha
Classifier: Intended Audience :: Developers
Classifier: License :: OSI Approved :: Apache Software License
Classifier: Natural Language :: English
Classifier: Operating System :: OS Independent
Classifier: Programming Language :: Python :: 3
Classifier: Programming Language :: Python :: 3.9
Classifier: Programming Language :: Python :: 3.10
Classifier: Programming Language :: Python :: 3.11
Classifier: Programming Language :: Python :: 3.12
Classifier: Programming Language :: Python :: 3.13
Classifier: Topic :: Software Development :: Libraries
Project-URL: Bug Tracker, https://github.com/python-kasa/kasa-crypt/issues
Project-URL: Changelog, https://github.com/python-kasa/kasa-crypt/blob/main/CHANGELOG.md
Project-URL: Repository, https://github.com/python-kasa/kasa-crypt
